blacklist/__init__.py
blacklist/admin.py
blacklist/app_settings.py
blacklist/apps.py
blacklist/auth_hooks.py
blacklist/forms.py
blacklist/managers.py
blacklist/models.py
blacklist/providers.py
blacklist/signals.py
blacklist/tasks.py
blacklist/urls.py
blacklist/views.py
blacklist/management/commands/__init__.py
blacklist/management/commands/blacklist_state.py
blacklist/management/commands/blacklist_sync.py
blacklist/migrations/0001_initial.py
blacklist/migrations/__init__.py
blacklist/templates/blacklist/add_note.html
blacklist/templates/blacklist/base.html
blacklist/templates/blacklist/blacklist.html
blacklist/templates/blacklist/edit_note.html
blacklist/templates/blacklist/evenotes.html
blacklist/templates/blacklist/modal_add_comment.html
blacklist/templates/blacklist/modal_comments.html
blacklist/templates/blacklist/modal_edit_note.html
blacklist/templates/blacklist/search_name.html
blacklist/templatetags/__init__.py
blacklist/templatetags/blacklist_tags.py
blacklist/tests/test_access.py
tests/__init__.py
tests/celery.py
tests/test_settings.py
tests/urls.py
tests/views.py
allianceauth_blacklist-0.0.1a1.dist-info/LICENSE
allianceauth_blacklist-0.0.1a1.dist-info/METADATA
allianceauth_blacklist-0.0.1a1.dist-info/WHEEL
allianceauth_blacklist-0.0.1a1.dist-info/top_level.txt
allianceauth_blacklist-0.0.1a1.dist-info/RECORD
