Metadata-Version: 2.1
Name: allianceauth-blacklist
Version: 0.0.1a1
Summary: Alliance Auth Plugin
Home-page: https://github.com/Solar-Helix-Independent-Transport/allianceauth-blacklist
Author: AaronKable
Author-email: aaronkable@gmail.com
License: GNU General Public License v3 (GPLv3)
Platform: UNKNOWN
Classifier: Environment :: Web Environment
Classifier: Framework :: Django
Classifier: Intended Audience :: Developers
Classifier: License :: OSI Approved :: GNU General Public License v3 (GPLv3)
Classifier: Operating System :: OS Independent
Classifier: Programming Language :: Python :: 3.6
Classifier: Topic :: Internet :: WWW/HTTP
Classifier: Topic :: Internet :: WWW/HTTP :: Dynamic Content
Requires-Dist: allianceauth (>=2.8.0)
